{"title":"Netflix Korea ─ NAVER TV","url":"https://tv.naver.com/netflixkr/clips","favicon":"https://tv.naver.com/netflixkr/favicon.ico","elements":[{"title":"[넷플릭스] 도심을 박살내는 트롤을 피해 도망쳐라 | 트롤의 습격","contents":"2:21","link":"https://tv.naver.com/v/31433218","retrieved":1670462009144,"image":"https://phinf.pstatic.net/tvcast/20221208_154/hLzNG_1670461762292JrKEU_JPEG/1670461656455.jpg?type=f194_109_blend"},{"title":"[넷플릭스] 더 글로리 I 티저 예고편","contents":"1:30","link":"https://tv.naver.com/v/31404839","retrieved":1670462009145,"image":"https://phinf.pstatic.net/tvcast/20221207_232/JEXRT_16703811386309VgM1_JPEG/1670381129405.jpg?type=f194_109_blend"},{"title":"[넷플릭스] 더 패뷸러스 | 스페셜 심쿵 예고편","contents":"0:58","link":"https://tv.naver.com/v/31379716","retrieved":1670375739210,"image":"https://phinf.pstatic.net/tvcast/20221206_25/Y2M0p_16703088641788pgGk_JPEG/1670308699771.jpg?type=f194_109_blend"},{"title":"[넷플릭스] 해리와 메건 | 공식 예고편","contents":"1:16","link":"https://tv.naver.com/v/31369991","retrieved":1670294528448,"image":"https://phinf.pstatic.net/tvcast/20221206_286/kLH1o_1670291266421Kztep_JPEG/1670291233652.jpg?type=f194_109_blend"},{"title":"[넷플릭스] 마이코네 행복한 밥상 | 공식 예고편","contents":"2:25","link":"https://tv.naver.com/v/31343725","retrieved":1670221188737,"image":"https://phinf.pstatic.net/tvcast/20221205_254/fOm7k_16702198991268vRTF_JPEG/1670219843304.jpg?type=f194_109_blend"},{"title":"[넷플릭스] 아리스 인 보더랜드 시즌 2 | 공식 예고편","contents":"2:28","link":"https://tv.naver.com/v/31343678","retrieved":1670221188739,"image":"https://phinf.pstatic.net/tvcast/20221205_13/v5Mym_16702198249453oeY9_JPEG/1670219807375.jpg?type=f194_109_blend"},{"title":"[넷플릭스] 위쳐: 블러드 오리진 | 공식 예고편","contents":"2:34","link":"https://tv.naver.com/v/31343650","retrieved":1670221188741,"image":"https://phinf.pstatic.net/tvcast/20221205_194/sQO3i_1670219769470qKRhf_JPEG/1670219717324.jpg?type=f194_109_blend"},{"title":"[넷플릭스] 종이의 집: 공동경제구역 파트2 | 미공개 클립","contents":"1:38","link":"https://tv.naver.com/v/31335751","retrieved":1670208091477,"image":"https://phinf.pstatic.net/tvcast/20221205_224/4UAk4_1670204524565trBRm_JPEG/1670204357054.jpg?type=f194_109_blend"},{"title":"[넷플릭스] 해리와 메건 | 공식 티저 예고편","contents":"1:12","link":"https://tv.naver.com/v/31272376","retrieved":1669949270235,"image":"https://phinf.pstatic.net/tvcast/20221202_65/wvwaB_1669948480242ToAoj_JPEG/1669948233558.jpg?type=f194_109_blend"},{"title":"[넷플릭스] 이광수 김연경 진짜 남매 증거 제출합니다 | 코리아 넘버원","contents":"2:49","link":"https://tv.naver.com/v/31240688","retrieved":1669868432707,"image":"https://phinf.pstatic.net/tvcast/20221201_87/0UrG0_1669864923731XYFDC_JPEG/1669864886046.jpg?type=f194_109_blend"},{"title":"[넷플릭스] 김연경의 하드코어 예능 도전기 | 코리아 넘버원","contents":"2:29","link":"https://tv.naver.com/v/31240654","retrieved":1669868432709,"image":"https://phinf.pstatic.net/tvcast/20221201_128/CKxBC_1669864867690E6qG0_JPEG/1669864836866.jpg?type=f194_109_blend"},{"title":"[넷플릭스] 투 핫! 시즌 4 | 공식 예고편","contents":"2:11","link":"https://tv.naver.com/v/31240302","retrieved":1669868432711,"image":"https://phinf.pstatic.net/tvcast/20221201_265/FFCu1_16698642014200Mwqv_JPEG/1669864078837.jpg?type=f194_109_blend"},{"title":"[넷플릭스] 에밀리, 파리에 가다 시즌 3 | 공식 예고편","contents":"2:19","link":"https://tv.naver.com/v/31239037","retrieved":1669864172436,"image":"https://phinf.pstatic.net/tvcast/20221201_37/QXV4X_1669861932119Piusp_JPEG/1669861878624.jpg?type=f194_109_blend"},{"title":"[넷플릭스] 더 글로리  | 공개일 발표","contents":"0:49","link":"https://tv.naver.com/v/31218699","retrieved":1669858017823,"image":"https://phinf.pstatic.net/tvcast/20221130_249/ZNwIz_16697995151923MNyh_JPEG/1669799235768.jpg?type=f194_109_blend"},{"title":"[넷플릭스] 한국의 잔소리 장인 유재석을 모셨습니다 | 코리아 넘버원","contents":"3:13","link":"https://tv.naver.com/v/31143019","retrieved":1669616474450,"image":"https://phinf.pstatic.net/tvcast/20221128_253/J9Dxw_1669615721217L5sry_JPEG/1669615701341.jpg?type=f194_109_blend"},{"title":"[넷플릭스] 팀 버튼의 세계관 속 제나 오르테가 | 웬즈데이","contents":"2:12","link":"https://tv.naver.com/v/31142939","retrieved":1669616474452,"image":"https://phinf.pstatic.net/tvcast/20221128_52/dncf0_1669615565540kQjJa_JPEG/1669615487392.jpg?type=f194_109_blend"},{"title":"[넷플릭스] 종말의 발키리 시즌 2 | 공식 예고편","contents":"1:49","link":"https://tv.naver.com/v/31073678","retrieved":1669345294093,"image":"https://phinf.pstatic.net/tvcast/20221125_162/NRezB_1669344151170JV5mb_JPEG/1669344095590.jpg?type=f194_109_blend"},{"title":"[넷플릭스] 이광수를 빼고는 몸개그를 논하지 말라 | 코리아 넘버원","contents":"1:53","link":"https://tv.naver.com/v/31072067","retrieved":1669690353508,"image":"https://phinf.pstatic.net/tvcast/20221129_62/FaiXh_1669691367933LKq70_JPEG/1669691363148.jpg?type=f194_109_blend"},{"title":"[넷플릭스] 코리아 넘버원 | 3화 하이라이트","contents":"1:38","link":"https://tv.naver.com/v/31071803","retrieved":1669430996346,"image":"https://phinf.pstatic.net/tvcast/20221125_50/WvAzs_166934108231835bjd_JPEG/1669341079609.jpg?type=f194_109_blend"},{"title":"[넷플릭스] 꿈의 세계 무법자가 된 제이슨 모모아 | 슬럼버랜드","contents":"2:37","link":"https://tv.naver.com/v/31048478","retrieved":1669270848384,"image":"https://phinf.pstatic.net/tvcast/20221124_190/vG2zK_1669268285774LgmEO_JPEG/1669268242627.jpg?type=f194_109_blend"},{"title":"[넷플릭스] 거대한 미스터리를 마주한 케르베로스호의 승객들 | 1899","contents":"2:37","link":"https://tv.naver.com/v/31048446","retrieved":1669270848387,"image":"https://phinf.pstatic.net/tvcast/20221124_152/YJKJ3_1669268231433vHJUl_JPEG/1669268192504.jpg?type=f194_109_blend"},{"title":"[넷플릭스] 종이의 집: 공동경제구역 파트2 | 메인 예고편","contents":"1:39","link":"https://tv.naver.com/v/30982172","retrieved":1669166362523,"image":"https://phinf.pstatic.net/tvcast/20221122_195/yayUF_1669100441657rKFH3_JPEG/1669100122131.jpg?type=f194_109_blend"},{"title":"[넷플릭스] 일곱 개의 대죄: 원망의 에든버러 파트 1 | 공식 예고편","contents":"1:28","link":"https://tv.naver.com/v/30940310","retrieved":1669000589940,"image":"https://phinf.pstatic.net/tvcast/20221121_85/bcGPF_16689985274117mE51_JPEG/1668998413259.jpg?type=f194_109_blend"},{"title":"[넷플릭스] 《죠죠의 기묘한 모험 스톤 오션》 | 공식 예고편 #4","contents":"1:35","link":"https://tv.naver.com/v/30940250","retrieved":1669000589941,"image":"https://phinf.pstatic.net/tvcast/20221121_223/CNTmF_1668998390740RIJ3S_JPEG/1668998350868.jpg?type=f194_109_blend"},{"title":"[넷플릭스] 재벌가 비서였던 송중기가 막내아들로 회귀했다 l 재벌집 막내아들","contents":"6:14","link":"https://tv.naver.com/v/30940210","retrieved":1669000589943,"image":"https://phinf.pstatic.net/tvcast/20221121_159/fH8U2_1668998309528916b3_JPEG/1668998142115.jpg?type=f194_109_blend"},{"title":"[넷플릭스] 사이코패스 인간 혐오자 성윤오가 된 김영광 | 썸바디","contents":"2:18","link":"https://tv.naver.com/v/30938476","retrieved":1669000589948,"image":"https://phinf.pstatic.net/tvcast/20221121_72/x9oD5_1668994595246UgVS2_JPEG/1668994593063.jpg?type=f194_109_blend"},{"title":"[넷플릭스] 고등학생 천재 개발자가 만든 이상한 채팅 로봇 | 썸바디","contents":"2:23","link":"https://tv.naver.com/v/30888001","retrieved":1668770078459,"image":"https://phinf.pstatic.net/tvcast/20221118_179/cuOCT_1668769430082tKrG9_JPEG/1668769327614.jpg?type=f194_109_blend"},{"title":"[넷플릭스] 소닉 프라임 | 공식 예고편","contents":"2:11","link":"https://tv.naver.com/v/30879311","retrieved":1669000589958,"image":"https://phinf.pstatic.net/tvcast/20221118_146/PM2dV_16687512852873N9zE_JPEG/1668751211711.jpg?type=f194_109_blend"},{"title":"[넷플릭스] 더 리크루트 | 공식 예고편","contents":"2:20","link":"https://tv.naver.com/v/30846167","retrieved":1668666091360,"image":"https://phinf.pstatic.net/tvcast/20221117_266/LEkJ6_1668662972038yVbRk_JPEG/1668662864360.jpg?type=f194_109_blend"},{"title":"[넷플릭스] 퍼스트 러브 하츠코이 | 공식 예고편","contents":"2:30","link":"https://tv.naver.com/v/30782476","retrieved":1668619795828,"image":"https://phinf.pstatic.net/tvcast/20221115_130/birir_1668490707850aL8bp_JPEG/1668490672284.jpg?type=f194_109_blend"}]}